forumpaypy/__init__.py
forumpaypy/forumpay.py
forumpaypy/endpoints/__init__.py
forumpaypy/endpoints/base_endpoint.py
forumpaypy/endpoints/check_payment.py
forumpaypy/endpoints/endpoints.py
forumpaypy/endpoints/ping.py
forumpaypy/endpoints/request_parameters/__init__.py
forumpaypy/endpoints/request_parameters/parameter_requirement.py
forumpaypy/endpoints/request_parameters/parameter_restriction.py
forumpaypy/endpoints/request_parameters/request_parameter.py
forumpaypy/endpoints/request_parameters/request_parameter_list.py
forumpaypy/enums/__init__.py
forumpaypy/enums/content_type_enum.py
forumpaypy/enums/forumpay_base_url.py
forumpaypy/enums/http_method_enum.py
forumpaypy-0.0.1.dist-info/LICENSE
forumpaypy-0.0.1.dist-info/METADATA
forumpaypy-0.0.1.dist-info/WHEEL
forumpaypy-0.0.1.dist-info/top_level.txt
forumpaypy-0.0.1.dist-info/RECORD
